{
  "transactions": [
    {
      "account": "compteisa1",
      "amount": -60,
      "manualCategoryId": "400610",
      "currency": "€",
      "date": "2017-07-06T00:00:00Z",
      "demo": true,
      "label": "CABINET OSTEOKINESITHERAPIE"
    },
    {
      "account": "compteisa1",
      "amount": -60,
      "manualCategoryId": "400610",
      "currency": "€",
      "date": "2017-07-06T00:00:00Z",
      "demo": true,
      "label": "CABINET OSTEOKINESITHERAPIE"
    },
    {
      "account": "comptecla1",
      "amount": -60,
      "manualCategoryId": "400610",
      "currency": "€",
      "date": "2017-07-06T00:00:00Z",
      "demo": true,
      "label": "CABINET OSTEOKINESITHERAPIE"
    }
  ],
  "accounts": [
    {
      "_id": "compteisa1",
      "label": "Compte Isabelle 1",
      "institutionLabel": "HSBC"
    },
    {
      "_id": "comptecla1",
      "label": "Compte Claire 1",
      "institutionLabel": "CIC"
    }
  ]
}
